{
  "AppSettings": {
    "UserLoginExpireDay": 30, //用户登录过期时间设置,按天算,指在当前时间往后加的天数
    "UserCodeExpireSecond": 120, //用户验证时,发送的验证码过期时间配置,单位：秒
    "UserAddFriendTotalCount": 3000, //添加好友总数量上限
    "UserAddFriendDayCount": 30, //每天添加好友数量上限
    "UploadDirectory": "E:\\hwl-upload\\", //文件上传目录配置,值为当前计算机的绝对地址
    "FileAccessUrl": "http://10.61.8.23:8081/upload" //文件对外访问的地址配置,值以http://或者https://开头,upload可作为虚拟目录名
  },
  "RedisSettings": {
    "GroupUserTotalCount": 500, //群组好友总数量上限
    "UserDynamicRedisHosts": "127.0.0.1:6379,allowadmin=true,password=123456", //用户token配置
    "IMMessageRedisHosts": "127.0.0.1:6379,allowadmin=true,password=123456", //消息处理地址配置
    "CollectionRedisHosts": "127.0.0.1:6379,allowadmin=true,password=123456",
    "HWLManageSessionRedisHosts": "127.0.0.1:6379,allowAdmin=true,password=123456,defaultdatabase=0",
    "HWLManageSessionRedisInstance": "hwlmg:sessionid:",
    "HWLManageSessionTimeOut": 120 //minute
  },
  "IMSettings": {
    "IMHost": "127.0.0.1",
    "IMPort": 8081
  },
  "RabbitMQSettings": {
    "Host": "127.0.0.1",
    "Port": 5672,
    "UserName": "liytest",
    "Password": "ya.li.4321"
  },
  "ConnectionStrings": {
    "HWLDBConnectionString": "Data Source=.;Initial Catalog=zltest;Persist Security Info=True;User ID=sa;Password=WCNM.weiruan.2"
  },
  "LogSettings": {
    "LogDirectory": "hwl-logs",
    "EnableDebug": true,
    "EnableInfo": true,
    "EnableWarn": true,
    "EnableError": true,
    "EnableFatal": true
  }
}